README.md
setup.py
colorslogging/__init__.py
colorslogging/colorslogging.py
colorslogging/test.py
colorslogging.egg-info/PKG-INFO
colorslogging.egg-info/SOURCES.txt
colorslogging.egg-info/dependency_links.txt
colorslogging.egg-info/top_level.txt