Metadata-Version: 1.0
Name: colorslogging
Version: 0.0.1
Summary: a library for custom logging
Home-page: https://github.com/n00B-ToT/colorslogging
Author: n00b-tot
Author-email: shengta66396@163.com
License: MIT License
Keywords: logging logger
Platform: any
